multiecho/__init__.py
multiecho/_args.py
multiecho/combination.py
multiecho-0.30.data/data/share/man/man1/mecombine.1
multiecho-0.30.dist-info/METADATA
multiecho-0.30.dist-info/WHEEL
multiecho-0.30.dist-info/entry_points.txt
multiecho-0.30.dist-info/top_level.txt
multiecho-0.30.dist-info/RECORD
