Metadata-Version: 2.2
Name: multiecho
Version: 0.30
Summary: Combine multi-echoes from a multi-echo fMRI acquisition.
Home-page: https://github.com/Donders-Institute/multiecho
Author: Daniel Gomez
Author-email: dgomez1@mgh.harvard.edu
Maintainer: Marcel Zwiers
Maintainer-email: m.zwiers@donders.ru.nl
Keywords: mri,multi-echo,bids
Classifier: Intended Audience :: Developers
Classifier: License :: OSI Approved :: MIT License
Classifier: License :: OSI Approved :: Apache Software License
Classifier: Natural Language :: English
Classifier: Operating System :: OS Independent
Classifier: Programming Language :: Python :: 3
Classifier: Programming Language :: Python :: Implementation :: CPython
Requires-Dist: coloredlogs
Requires-Dist: numpy
Requires-Dist: nibabel
Dynamic: author
Dynamic: author-email
Dynamic: classifier
Dynamic: description
Dynamic: description-content-type
Dynamic: home-page
Dynamic: keywords
Dynamic: maintainer
Dynamic: maintainer-email
Dynamic: requires-dist
Dynamic: summary
